windowsshareaccess/__init__.py
windowsshareaccess/settings.py
windowsshareaccess-0.9.dist-info/LICENSE
windowsshareaccess-0.9.dist-info/METADATA
windowsshareaccess-0.9.dist-info/WHEEL
windowsshareaccess-0.9.dist-info/top_level.txt
windowsshareaccess-0.9.dist-info/RECORD
