Metadata-Version: 2.1
Name: windowsshareaccess
Version: 0.9
Summary: Wrapper to access Windows share drive
Home-page: UNKNOWN
Author: Tim Watson, Jamie Wooltorton, Henry Jolliffe, Ryszard Dudek, Clare Ford
Author-email: tswatson123@gmail.com
License: MIT
Platform: UNKNOWN
Requires-Dist: pysmb (==1.1.25)
